{"rotation":"0","node":[{"index":"0","class":"android.widget.LinearLayout","package":"com.android.systemui","checkable":"false","checked":"false","clickable":"false","enabled":"true","focusable":"false","focused":"false","scrollable":"false","long-clickable":"false","password":"false","selected":"false","bounds":"[0,1794][1080,1920]","node":{"index":"0","resource-id":"com.android.systemui:id/rot0","class":"android.widget.FrameLayout","package":"com.android.systemui","checkable":"false","checked":"false","clickable":"false","enabled":"true","focusable":"false","focused":"false","scrollable":"false","long-clickable":"false","password":"false","selected":"false","bounds":"[0,1794][1080,1920]","node":[{"index":"0","resource-id":"com.android.systemui:id/deadzone","class":"android.view.View","package":"com.android.systemui","checkable":"false","checked":"false","clickable":"false","enabled":"true","focusable":"false","focused":"false","scrollable":"false","long-clickable":"false","password":"false","selected":"false","bounds":"[0,1794][1080,1920]"},{"index":"1","resource-id":"com.android.systemui:id/nav_buttons","class":"android.widget.LinearLayout","package":"com.android.systemui","checkable":"false","checked":"false","clickable":"false","enabled":"true","focusable":"false","focused":"false","scrollable":"false","long-clickable":"false","password":"false","selected":"false","bounds":"[0,1794][1080,1920]","node":[{"index":"0","resource-id":"com.android.systemui:id/back","class":"android.widget.ImageView","package":"com.android.systemui","content-desc":"Back","checkable":"false","checked":"false","clickable":"true","enabled":"true","focusable":"false","focused":"false","scrollable":"false","long-clickable":"true","password":"false","selected":"false","bounds":"[131,1794][341,1920]"},{"index":"1","resource-id":"com.android.systemui:id/home","class":"android.widget.ImageView","package":"com.android.systemui","content-desc":"Home","checkable":"false","checked":"false","clickable":"true","enabled":"true","focusable":"false","focused":"false","scrollable":"false","long-clickable":"true","password":"false","selected":"false","bounds":"[435,1794][645,1920]"},{"index":"2","resource-id":"com.android.systemui:id/recent_apps","class":"android.widget.ImageView","package":"com.android.systemui","content-desc":"Overview","checkable":"false","checked":"false","clickable":"true","enabled":"true","focusable":"false","focused":"false","scrollable":"false","long-clickable":"true","password":"false","selected":"false","bounds":"[739,1794][949,1920]"},{"index":"3","class":"android.widget.FrameLayout","package":"com.android.systemui","checkable":"false","checked":"false","clickable":"false","enabled":"true","focusable":"false","focused":"false","scrollable":"false","long-clickable":"false","password":"false","selected":"false","bounds":"[949,1794][1080,1920]"}]}]}},{"index":"0","class":"android.widget.FrameLayout","package":"com.android.systemui","checkable":"false","checked":"false","clickable":"false","enabled":"true","focusable":"false","focused":"false","scrollable":"false","long-clickable":"false","password":"false","selected":"false","bounds":"[0,0][1080,63]","node":[{"index":"1","resource-id":"com.android.systemui:id/status_bar","class":"android.widget.FrameLayout","package":"com.android.systemui","checkable":"false","checked":"false","clickable":"false","enabled":"true","focusable":"false","focused":"false","scrollable":"false","long-clickable":"false","password":"false","selected":"false","bounds":"[0,0][1080,63]","node":{"index":"0","resource-id":"com.android.systemui:id/status_bar_contents","class":"android.widget.LinearLayout","package":"com.android.systemui","checkable":"false","checked":"false","clickable":"false","enabled":"true","focusable":"false","focused":"false","scrollable":"false","long-clickable":"false","password":"false","selected":"false","bounds":"[0,0][1080,63]","node":[{"index":"0","resource-id":"com.android.systemui:id/notification_icon_area","class":"android.widget.FrameLayout","package":"com.android.systemui","checkable":"false","checked":"false","clickable":"false","enabled":"true","focusable":"false","focused":"false","scrollable":"false","long-clickable":"false","password":"false","selected":"false","bounds":"[16,0][869,63]","node":{"index":"0","resource-id":"com.android.systemui:id/notification_icon_area_inner","class":"android.widget.LinearLayout","package":"com.android.systemui","checkable":"false","checked":"false","clickable":"false","enabled":"true","focusable":"false","focused":"false","scrollable":"false","long-clickable":"false","password":"false","selected":"false","bounds":"[16,0][869,63]","node":{"index":"0","resource-id":"com.android.systemui:id/notificationIcons","class":"android.widget.LinearLayout","package":"com.android.systemui","checkable":"false","checked":"false","clickable":"false","enabled":"true","focusable":"false","focused":"false","scrollable":"false","long-clickable":"false","password":"false","selected":"false","bounds":"[16,0][835,63]","node":[{"index":"0","class":"android.widget.ImageView","package":"com.android.systemui","checkable":"false","checked":"false","clickable":"false","enabled":"true","focusable":"false","focused":"false","scrollable":"false","long-clickable":"false","password":"false","selected":"false","bounds":"[25,9][70,54]"},{"index":"1","class":"android.widget.ImageView","package":"com.android.systemui","content-desc":"USB debugging connected","checkable":"false","checked":"false","clickable":"false","enabled":"true","focusable":"false","focused":"false","scrollable":"false","long-clickable":"false","password":"false","selected":"false","bounds":"[88,9][133,54]"}]}}},{"index":"1","resource-id":"com.android.systemui:id/system_icon_area","class":"android.widget.LinearLayout","package":"com.android.systemui","checkable":"false","checked":"false","clickable":"false","enabled":"true","focusable":"false","focused":"false","scrollable":"false","long-clickable":"false","password":"false","selected":"false","bounds":"[869,0][1059,63]","node":[{"index":"0","resource-id":"com.android.systemui:id/system_icons","class":"android.widget.LinearLayout","package":"com.android.systemui","checkable":"false","checked":"false","clickable":"false","enabled":"true","focusable":"false","focused":"false","scrollable":"false","long-clickable":"false","password":"false","selected":"false","bounds":"[869,0][968,63]","node":[{"index":"1","resource-id":"com.android.systemui:id/signal_cluster","class":"android.widget.LinearLayout","package":"com.android.systemui","checkable":"false","checked":"false","clickable":"false","enabled":"true","focusable":"false","focused":"false","scrollable":"false","long-clickable":"false","password":"false","selected":"false","bounds":"[876,9][943,53]","node":{"index":"0","resource-id":"com.android.systemui:id/mobile_signal_group","class":"android.widget.LinearLayout","package":"com.android.systemui","checkable":"false","checked":"false","clickable":"false","enabled":"true","focusable":"false","focused":"false","scrollable":"false","long-clickable":"false","password":"false","selected":"false","bounds":"[876,9][925,53]","node":{"index":"0","resource-id":"com.android.systemui:id/mobile_combo","class":"android.widget.FrameLayout","package":"com.android.systemui","content-desc":"LTE Phone two bars.","checkable":"false","checked":"false","clickable":"false","enabled":"true","focusable":"false","focused":"false","scrollable":"false","long-clickable":"false","password":"false","selected":"false","bounds":"[876,9][925,53]","node":[{"index":"1","resource-id":"com.android.systemui:id/mobile_signal","class":"android.widget.ImageView","package":"com.android.systemui","checkable":"false","checked":"false","clickable":"false","enabled":"true","focusable":"false","focused":"false","scrollable":"false","long-clickable":"false","password":"false","selected":"false","bounds":"[876,9][925,53]"},{"index":"2","resource-id":"com.android.systemui:id/mobile_type","class":"android.widget.ImageView","package":"com.android.systemui","checkable":"false","checked":"false","clickable":"false","enabled":"true","focusable":"false","focused":"false","scrollable":"false","long-clickable":"false","password":"false","selected":"false","bounds":"[876,9][900,53]"}]}}},{"index":"2","resource-id":"com.android.systemui:id/battery","class":"android.view.View","package":"com.android.systemui","content-desc":"Battery 100 percent.","checkable":"false","checked":"false","clickable":"false","enabled":"true","focusable":"false","focused":"false","scrollable":"false","long-clickable":"false","password":"false","selected":"false","bounds":"[943,12][968,50]"}]},{"index":"1","text":"6:06","resource-id":"com.android.systemui:id/clock","class":"android.widget.TextView","package":"com.android.systemui","checkable":"false","checked":"false","clickable":"false","enabled":"true","focusable":"false","focused":"false","scrollable":"false","long-clickable":"false","password":"false","selected":"false","bounds":"[968,0][1059,63]"}]}]}},{"index":"2","resource-id":"com.android.systemui:id/scrim_behind","class":"android.view.View","package":"com.android.systemui","checkable":"false","checked":"false","clickable":"false","enabled":"true","focusable":"false","focused":"false","scrollable":"false","long-clickable":"false","password":"false","selected":"false","bounds":"[0,0][1080,63]"},{"index":"3","resource-id":"com.android.systemui:id/panel_holder","class":"android.widget.FrameLayout","package":"com.android.systemui","checkable":"false","checked":"false","clickable":"false","enabled":"true","focusable":"false","focused":"false","scrollable":"false","long-clickable":"false","password":"false","selected":"false","bounds":"[0,0][1080,63]"},{"index":"4","resource-id":"com.android.systemui:id/scrim_in_front","class":"android.view.View","package":"com.android.systemui","checkable":"false","checked":"false","clickable":"false","enabled":"true","focusable":"false","focused":"false","scrollable":"false","long-clickable":"false","password":"false","selected":"false","bounds":"[0,0][1080,63]"}]},{"index":"0","class":"android.widget.FrameLayout","package":"com.ZhuluX","checkable":"false","checked":"false","clickable":"false","enabled":"true","focusable":"false","focused":"false","scrollable":"false","long-clickable":"false","password":"false","selected":"false","bounds":"[0,0][1080,1794]","node":{"index":"0","class":"android.widget.LinearLayout","package":"com.ZhuluX","checkable":"false","checked":"false","clickable":"false","enabled":"true","focusable":"false","focused":"false","scrollable":"false","long-clickable":"false","password":"false","selected":"false","bounds":"[0,0][1080,1794]","node":{"index":"0","resource-id":"android:id/content","class":"android.widget.FrameLayout","package":"com.ZhuluX","checkable":"false","checked":"false","clickable":"false","enabled":"true","focusable":"false","focused":"false","scrollable":"false","long-clickable":"false","password":"false","selected":"false","bounds":"[0,63][1080,1794]","node":{"index":"0","class":"android.widget.FrameLayout","package":"com.ZhuluX","checkable":"false","checked":"false","clickable":"false","enabled":"true","focusable":"false","focused":"false","scrollable":"false","long-clickable":"false","password":"false","selected":"false","bounds":"[0,63][1080,1794]","node":{"index":"0","class":"android.view.ViewGroup","package":"com.ZhuluX","checkable":"false","checked":"false","clickable":"false","enabled":"true","focusable":"false","focused":"false","scrollable":"false","long-clickable":"false","password":"false","selected":"false","bounds":"[0,63][1080,1794]","node":{"index":"0","class":"android.view.ViewGroup","package":"com.ZhuluX","checkable":"false","checked":"false","clickable":"false","enabled":"true","focusable":"false","focused":"false","scrollable":"false","long-clickable":"false","password":"false","selected":"false","bounds":"[0,63][1080,1794]","node":{"index":"0","class":"android.view.ViewGroup","package":"com.ZhuluX","checkable":"false","checked":"false","clickable":"false","enabled":"true","focusable":"false","focused":"false","scrollable":"false","long-clickable":"false","password":"false","selected":"false","bounds":"[0,63][1080,1794]","node":{"index":"0","class":"android.view.ViewGroup","package":"com.ZhuluX","checkable":"false","checked":"false","clickable":"false","enabled":"true","focusable":"false","focused":"false","scrollable":"false","long-clickable":"false","password":"false","selected":"false","bounds":"[0,63][1080,1794]","node":{"index":"0","class":"android.view.ViewGroup","package":"com.ZhuluX","checkable":"false","checked":"false","clickable":"false","enabled":"true","focusable":"false","focused":"false","scrollable":"false","long-clickable":"false","password":"false","selected":"false","bounds":"[0,63][1080,1794]","node":{"index":"0","class":"android.view.ViewGroup","package":"com.ZhuluX","checkable":"false","checked":"false","clickable":"false","enabled":"true","focusable":"false","focused":"false","scrollable":"false","long-clickable":"false","password":"false","selected":"false","bounds":"[0,63][1080,1794]","node":[{"index":"0","class":"android.view.ViewGroup","package":"com.ZhuluX","checkable":"false","checked":"false","clickable":"false","enabled":"true","focusable":"false","focused":"false","scrollable":"false","long-clickable":"false","password":"false","selected":"false","bounds":"[2,106][1028,1751]","node":[{"index":"0","class":"android.view.ViewGroup","package":"com.ZhuluX","checkable":"false","checked":"false","clickable":"false","enabled":"true","focusable":"false","focused":"false","scrollable":"false","long-clickable":"false","password":"false","selected":"false","bounds":"[2,106][1028,206]","node":[{"index":"0","class":"android.view.ViewGroup","package":"com.ZhuluX","checkable":"false","checked":"false","clickable":"false","enabled":"true","focusable":"true","focused":"false","scrollable":"false","long-clickable":"false","password":"false","selected":"false","bounds":"[39,117][904,186]","node":{"index":"0","class":"android.view.ViewGroup","package":"com.ZhuluX","checkable":"false","checked":"false","clickable":"false","enabled":"true","focusable":"false","focused":"false","scrollable":"false","long-clickable":"false","password":"false","selected":"false","bounds":"[39,117][904,186]","node":[{"index":"0","text":"","class":"android.widget.TextView","package":"com.ZhuluX","checkable":"false","checked":"false","clickable":"false","enabled":"true","focusable":"false","focused":"false","scrollable":"false","long-clickable":"false","password":"false","selected":"false","bounds":"[64,125][114,178]"},{"index":"1","text":"搜索业内最全项目数据库","class":"android.widget.EditText","package":"com.ZhuluX","checkable":"false","checked":"false","clickable":"true","enabled":"false","focusable":"true","focused":"false","scrollable":"false","long-clickable":"true","password":"false","selected":"false","bounds":"[114,117][903,186]"}]}},{"index":"1","class":"android.view.ViewGroup","package":"com.ZhuluX","checkable":"false","checked":"false","clickable":"false","enabled":"true","focusable":"true","focused":"false","scrollable":"false","long-clickable":"false","password":"false","selected":"false","bounds":"[903,125][990,178]","node":{"index":"0","class":"android.widget.ImageView","package":"com.ZhuluX","checkable":"false","checked":"false","clickable":"false","enabled":"true","focusable":"false","focused":"false","scrollable":"false","long-clickable":"false","password":"false","selected":"false","bounds":"[940,125][990,178]"}}]},{"index":"1","class":"android.view.ViewGroup","package":"com.ZhuluX","checkable":"false","checked":"false","clickable":"false","enabled":"true","focusable":"false","focused":"false","scrollable":"false","long-clickable":"false","password":"false","selected":"false","bounds":"[2,206][1028,1751]","node":[{"index":"0","class":"android.view.ViewGroup","package":"com.ZhuluX","checkable":"false","checked":"false","clickable":"false","enabled":"true","focusable":"false","focused":"false","scrollable":"false","long-clickable":"false","password":"false","selected":"false","bounds":"[2,206][1028,274]","node":{"index":"0","class":"android.view.ViewGroup","package":"com.ZhuluX","checkable":"false","checked":"false","clickable":"false","enabled":"true","focusable":"false","focused":"false","scrollable":"false","long-clickable":"false","password":"false","selected":"false","bounds":"[2,206][433,274]","node":[{"index":"0","class":"android.view.ViewGroup","package":"com.ZhuluX","checkable":"false","checked":"false","clickable":"false","enabled":"true","focusable":"true","focused":"false","scrollable":"false","long-clickable":"false","password":"false","selected":"false","bounds":"[39,206][180,274]","node":[{"index":"0","text":"逐鹿甄选","class":"android.widget.TextView","package":"com.ZhuluX","checkable":"false","checked":"false","clickable":"false","enabled":"true","focusable":"false","focused":"false","scrollable":"false","long-clickable":"false","password":"false","selected":"false","bounds":"[39,206][180,254]"},{"index":"1","class":"android.view.ViewGroup","package":"com.ZhuluX","checkable":"false","checked":"false","clickable":"false","enabled":"true","focusable":"false","focused":"false","scrollable":"false","long-clickable":"false","password":"false","selected":"false","bounds":"[62,262][156,267]"}]},{"index":"1","class":"android.view.ViewGroup","package":"com.ZhuluX","checkable":"false","checked":"false","clickable":"false","enabled":"true","focusable":"true","focused":"false","scrollable":"false","long-clickable":"false","password":"false","selected":"false","bounds":"[255,206][395,274]","node":{"index":"0","text":"本周上新","class":"android.widget.TextView","package":"com.ZhuluX","checkable":"false","checked":"false","clickable":"false","enabled":"true","focusable":"false","focused":"false","scrollable":"false","long-clickable":"false","password":"false","selected":"false","bounds":"[255,206][395,254]"}}]}},{"index":"1","class":"android.support.v4.view.ViewPager","package":"com.ZhuluX","checkable":"false","checked":"false","clickable":"false","enabled":"true","focusable":"true","focused":"false","scrollable":"true","long-clickable":"false","password":"false","selected":"false","bounds":"[2,274][1028,1751]","node":{"index":"0","class":"android.view.ViewGroup","package":"com.ZhuluX","checkable":"false","checked":"false","clickable":"false","enabled":"true","focusable":"false","focused":"false","scrollable":"false","long-clickable":"false","password":"false","selected":"false","bounds":"[2,274][1028,1751]","node":{"index":"0","class":"android.view.ViewGroup","package":"com.ZhuluX","checkable":"false","checked":"false","clickable":"false","enabled":"true","focusable":"false","focused":"false","scrollable":"false","long-clickable":"false","password":"false","selected":"false","bounds":"[2,274][1028,1751]","node":{"index":"0","class":"android.widget.ScrollView","package":"com.ZhuluX","checkable":"false","checked":"false","clickable":"false","enabled":"true","focusable":"true","focused":"false","scrollable":"true","long-clickable":"false","password":"false","selected":"false","bounds":"[2,274][1028,1751]","node":{"index":"0","class":"android.view.ViewGroup","package":"com.ZhuluX","checkable":"false","checked":"false","clickable":"false","enabled":"true","focusable":"false","focused":"false","scrollable":"false","long-clickable":"false","password":"false","selected":"false","bounds":"[2,274][1028,1751]","node":[{"index":"0","class":"android.view.ViewGroup","package":"com.ZhuluX","checkable":"false","checked":"false","clickable":"false","enabled":"true","focusable":"false","focused":"false","scrollable":"false","long-clickable":"false","password":"false","selected":"false","bounds":"[2,274][1028,494]","node":{"index":"0","class":"android.view.ViewGroup","package":"com.ZhuluX","checkable":"false","checked":"false","clickable":"false","enabled":"true","focusable":"true","focused":"false","scrollable":"false","long-clickable":"false","password":"false","selected":"false","bounds":"[2,274][1028,494]","node":{"index":"0","class":"android.view.ViewGroup","package":"com.ZhuluX","checkable":"false","checked":"false","clickable":"false","enabled":"true","focusable":"false","focused":"false","scrollable":"false","long-clickable":"false","password":"false","selected":"false","bounds":"[2,274][1028,494]","node":{"index":"0","class":"android.view.ViewGroup","package":"com.ZhuluX","checkable":"false","checked":"false","clickable":"false","enabled":"true","focusable":"false","focused":"false","scrollable":"false","long-clickable":"false","password":"false","selected":"false","bounds":"[2,274][1028,494]","node":[{"index":"7","class":"android.widget.TextView","package":"com.ZhuluX","checkable":"false","checked":"false","clickable":"false","enabled":"true","focusable":"false","focused":"false","scrollable":"false","long-clickable":"false","password":"false","selected":"false","bounds":"[39,292][991,308]"},{"index":"8","text":"详细地址略 · 天使/种子轮 · ","class":"android.widget.TextView","package":"com.ZhuluX","checkable":"false","checked":"false","clickable":"false","enabled":"true","focusable":"false","focused":"false","scrollable":"false","long-clickable":"false","password":"false","selected":"false","bounds":"[39,328][991,368]"},{"index":"9","class":"android.view.ViewGroup","package":"com.ZhuluX","checkable":"false","checked":"false","clickable":"false","enabled":"true","focusable":"false","focused":"false","scrollable":"false","long-clickable":"false","password":"false","selected":"false","bounds":"[39,388][143,457]","node":{"index":"0","text":"金融","class":"android.widget.TextView","package":"com.ZhuluX","checkable":"false","checked":"false","clickable":"false","enabled":"true","focusable":"false","focused":"false","scrollable":"false","long-clickable":"false","password":"false","selected":"false","bounds":"[60,402][121,443]"}}]}}}},{"index":"1","class":"android.view.ViewGroup","package":"com.ZhuluX","checkable":"false","checked":"false","clickable":"false","enabled":"true","focusable":"false","focused":"false","scrollable":"false","long-clickable":"false","password":"false","selected":"false","bounds":"[2,494][1028,1425]","node":[{"index":"0","class":"android.view.ViewGroup","package":"com.ZhuluX","checkable":"false","checked":"false","clickable":"false","enabled":"true","focusable":"true","focused":"false","scrollable":"false","long-clickable":"false","password":"false","selected":"false","bounds":"[2,494][1028,833]","node":{"index":"0","class":"android.view.ViewGroup","package":"com.ZhuluX","checkable":"false","checked":"false","clickable":"false","enabled":"true","focusable":"false","focused":"false","scrollable":"false","long-clickable":"false","password":"false","selected":"false","bounds":"[2,494][1028,833]","node":[{"index":"0","class":"android.view.ViewGroup","package":"com.ZhuluX","checkable":"false","checked":"false","clickable":"false","enabled":"true","focusable":"false","focused":"false","scrollable":"false","long-clickable":"false","password":"false","selected":"false","bounds":"[2,519][1028,832]","node":[{"index":"0","class":"android.widget.ImageView","package":"com.ZhuluX","checkable":"false","checked":"false","clickable":"false","enabled":"true","focusable":"false","focused":"false","scrollable":"false","long-clickable":"false","password":"false","selected":"false","bounds":"[39,567][139,667]"},{"index":"1","class":"android.view.ViewGroup","package":"com.ZhuluX","checkable":"false","checked":"false","clickable":"false","enabled":"true","focusable":"false","focused":"false","scrollable":"false","long-clickable":"false","password":"false","selected":"false","bounds":"[164,556][346,617]","node":{"index":"0","text":"创冰科技","class":"android.widget.TextView","package":"com.ZhuluX","checkable":"false","checked":"false","clickable":"false","enabled":"true","focusable":"false","focused":"false","scrollable":"false","long-clickable":"false","password":"false","selected":"false","bounds":"[164,556][346,617]"}},{"index":"2","class":"android.view.ViewGroup","package":"com.ZhuluX","checkable":"false","checked":"false","clickable":"false","enabled":"true","focusable":"false","focused":"false","scrollable":"false","long-clickable":"false","password":"false","selected":"false","bounds":"[358,561][408,612]","node":{"index":"0","text":"FA","class":"android.widget.TextView","package":"com.ZhuluX","checkable":"false","checked":"false","clickable":"false","enabled":"true","focusable":"false","focused":"false","scrollable":"false","long-clickable":"false","password":"false","selected":"false","bounds":"[366,566][400,607]"}},{"index":"4","class":"android.widget.ImageView","package":"com.ZhuluX","checkable":"false","checked":"false","clickable":"false","enabled":"true","focusable":"false","focused":"false","scrollable":"false","long-clickable":"false","password":"false","selected":"false","bounds":"[164,643][184,672]"},{"index":"5","text":"领跑竞品 · 名企高管","class":"android.widget.TextView","package":"com.ZhuluX","checkable":"false","checked":"false","clickable":"false","enabled":"true","focusable":"false","focused":"false","scrollable":"false","long-clickable":"false","password":"false","selected":"false","bounds":"[196,637][462,678]"},{"index":"7","class":"android.widget.TextView","package":"com.ZhuluX","checkable":"false","checked":"false","clickable":"false","enabled":"true","focusable":"false","focused":"false","scrollable":"false","long-clickable":"false","password":"false","selected":"false","bounds":"[39,698][991,714]"},{"index":"8","text":" · PreA/A轮 · 3000 - 3997万人民币","class":"android.widget.TextView","package":"com.ZhuluX","checkable":"false","checked":"false","clickable":"false","enabled":"true","focusable":"false","focused":"false","scrollable":"false","long-clickable":"false","password":"false","selected":"false","bounds":"[39,734][991,775]"}]},{"index":"1","class":"android.widget.ImageView","package":"com.ZhuluX","checkable":"false","checked":"false","clickable":"false","enabled":"true","focusable":"false","focused":"false","scrollable":"false","long-clickable":"false","password":"false","selected":"false","bounds":"[948,519][1028,596]"}]}},{"index":"1","class":"android.view.ViewGroup","package":"com.ZhuluX","checkable":"false","checked":"false","clickable":"false","enabled":"true","focusable":"false","focused":"false","scrollable":"false","long-clickable":"false","password":"false","selected":"false","bounds":"[2,833][1028,1425]","node":[{"index":"0","text":"精选机构","class":"android.widget.TextView","package":"com.ZhuluX","checkable":"false","checked":"false","clickable":"false","enabled":"true","focusable":"false","focused":"false","scrollable":"false","long-clickable":"false","password":"false","selected":"false","bounds":"[39,870][161,911]"},{"index":"1","class":"android.widget.HorizontalScrollView","package":"com.ZhuluX","checkable":"false","checked":"false","clickable":"false","enabled":"true","focusable":"true","focused":"false","scrollable":"true","long-clickable":"false","password":"false","selected":"false","bounds":"[2,949][1028,1425]","node":{"index":"0","class":"android.view.ViewGroup","package":"com.ZhuluX","checkable":"false","checked":"false","clickable":"false","enabled":"true","focusable":"false","focused":"false","scrollable":"false","long-clickable":"false","password":"false","selected":"false","bounds":"[2,949][1028,1425]","node":[{"index":"2","class":"android.view.ViewGroup","package":"com.ZhuluX","checkable":"false","checked":"false","clickable":"false","enabled":"true","focusable":"true","focused":"false","scrollable":"false","long-clickable":"false","password":"false","selected":"false","bounds":"[2,949][291,1423]","node":[{"index":"0","class":"android.widget.ImageView","package":"com.ZhuluX","checkable":"false","checked":"false","clickable":"false","enabled":"true","focusable":"false","focused":"false","scrollable":"false","long-clickable":"false","password":"false","selected":"false","bounds":"[49,1011][159,1120]"},{"index":"1","text":"中后台","class":"android.widget.TextView","package":"com.ZhuluX","checkable":"false","checked":"false","clickable":"false","enabled":"true","focusable":"false","focused":"false","scrollable":"false","long-clickable":"false","password":"false","selected":"false","bounds":"[44,1132][164,1177]"},{"index":"2","text":"金融","class":"android.widget.TextView","package":"com.ZhuluX","checkable":"false","checked":"false","clickable":"false","enabled":"true","focusable":"false","focused":"false","scrollable":"false","long-clickable":"false","password":"false","selected":"false","bounds":"[73,1190][134,1236]"},{"index":"3","text":"0 个项目","class":"android.widget.TextView","package":"com.ZhuluX","checkable":"false","checked":"false","clickable":"false","enabled":"true","focusable":"false","focused":"false","scrollable":"false","long-clickable":"false","password":"false","selected":"false","bounds":"[46,1248][162,1289]"},{"index":"4","class":"android.view.ViewGroup","package":"com.ZhuluX","content-desc":"+ 订阅","checkable":"false","checked":"false","clickable":"false","enabled":"true","focusable":"true","focused":"false","scrollable":"false","long-clickable":"false","password":"false","selected":"false","bounds":"[2,1326][264,1386]","node":{"index":"0","text":"+ 订阅","class":"android.widget.TextView","package":"com.ZhuluX","checkable":"false","checked":"false","clickable":"false","enabled":"true","focusable":"false","focused":"false","scrollable":"false","long-clickable":"false","password":"false","selected":"false","bounds":"[2,1332][263,1380]"}}]},{"index":"3","class":"android.view.ViewGroup","package":"com.ZhuluX","checkable":"false","checked":"false","clickable":"false","enabled":"true","focusable":"true","focused":"false","scrollable":"false","long-clickable":"false","password":"false","selected":"false","bounds":"[316,949][690,1423]","node":[{"index":"0","class":"android.widget.ImageView","package":"com.ZhuluX","checkable":"false","checked":"false","clickable":"false","enabled":"true","focusable":"false","focused":"false","scrollable":"false","long-clickable":"false","password":"false","selected":"false","bounds":"[448,1011][558,1120]"},{"index":"1","text":"车房金融","class":"android.widget.TextView","package":"com.ZhuluX","checkable":"false","checked":"false","clickable":"false","enabled":"true","focusable":"false","focused":"false","scrollable":"false","long-clickable":"false","password":"false","selected":"false","bounds":"[423,1132][583,1177]"},{"index":"2","text":"工具软件","class":"android.widget.TextView","package":"com.ZhuluX","checkable":"false","checked":"false","clickable":"false","enabled":"true","focusable":"false","focused":"false","scrollable":"false","long-clickable":"false","password":"false","selected":"false","bounds":"[442,1190][564,1236]"},{"index":"3","text":"0 个项目","class":"android.widget.TextView","package":"com.ZhuluX","checkable":"false","checked":"false","clickable":"false","enabled":"true","focusable":"false","focused":"false","scrollable":"false","long-clickable":"false","password":"false","selected":"false","bounds":"[445,1248][561,1289]"},{"index":"4","class":"android.view.ViewGroup","package":"com.ZhuluX","content-desc":"+ 订阅","checkable":"false","checked":"false","clickable":"false","enabled":"true","focusable":"true","focused":"false","scrollable":"false","long-clickable":"false","password":"false","selected":"false","bounds":"[342,1326][663,1386]","node":{"index":"0","text":"+ 订阅","class":"android.widget.TextView","package":"com.ZhuluX","checkable":"false","checked":"false","clickable":"false","enabled":"true","focusable":"false","focused":"false","scrollable":"false","long-clickable":"false","password":"false","selected":"false","bounds":"[345,1332][662,1380]"}}]},{"index":"4","class":"android.view.ViewGroup","package":"com.ZhuluX","checkable":"false","checked":"false","clickable":"false","enabled":"true","focusable":"true","focused":"false","scrollable":"false","long-clickable":"false","password":"false","selected":"false","bounds":"[690,949][1028,1425]","node":{"index":"0","class":"android.view.ViewGroup","package":"com.ZhuluX","checkable":"false","checked":"false","clickable":"false","enabled":"true","focusable":"false","focused":"false","scrollable":"false","long-clickable":"false","password":"false","selected":"false","bounds":"[715,949][1028,1423]","node":[{"index":"0","class":"android.widget.ImageView","package":"com.ZhuluX","checkable":"false","checked":"false","clickable":"false","enabled":"true","focusable":"false","focused":"false","scrollable":"false","long-clickable":"false","password":"false","selected":"false","bounds":"[827,1071][977,1221]"},{"index":"1","text":"查看全部机构","class":"android.widget.TextView","package":"com.ZhuluX","checkable":"false","checked":"false","clickable":"false","enabled":"true","focusable":"false","focused":"false","scrollable":"false","long-clickable":"false","password":"false","selected":"false","bounds":"[811,1259][993,1299]"}]}}]}}]}]},{"index":"2","class":"android.view.ViewGroup","package":"com.ZhuluX","checkable":"false","checked":"false","clickable":"false","enabled":"true","focusable":"false","focused":"false","scrollable":"false","long-clickable":"false","password":"false","selected":"false","bounds":"[2,1425][1028,1751]","node":{"index":"0","class":"android.view.ViewGroup","package":"com.ZhuluX","checkable":"false","checked":"false","clickable":"false","enabled":"true","focusable":"true","focused":"false","scrollable":"false","long-clickable":"false","password":"false","selected":"false","bounds":"[2,1425][1028,1751]","node":[{"index":"0","class":"android.view.ViewGroup","package":"com.ZhuluX","checkable":"false","checked":"false","clickable":"false","enabled":"true","focusable":"false","focused":"false","scrollable":"false","long-clickable":"false","password":"false","selected":"false","bounds":"[2,1450][1028,1751]","node":[{"index":"0","class":"android.widget.ImageView","package":"com.ZhuluX","checkable":"false","checked":"false","clickable":"false","enabled":"true","focusable":"false","focused":"false","scrollable":"false","long-clickable":"false","password":"false","selected":"false","bounds":"[39,1498][139,1598]"},{"index":"1","class":"android.view.ViewGroup","package":"com.ZhuluX","checkable":"false","checked":"false","clickable":"false","enabled":"true","focusable":"false","focused":"false","scrollable":"false","long-clickable":"false","password":"false","selected":"false","bounds":"[164,1487][345,1548]","node":{"index":"0","text":"DogFone","class":"android.widget.TextView","package":"com.ZhuluX","checkable":"false","checked":"false","clickable":"false","enabled":"true","focusable":"false","focused":"false","scrollable":"false","long-clickable":"false","password":"false","selected":"false","bounds":"[164,1487][345,1548]"}},{"index":"2","class":"android.view.ViewGroup","package":"com.ZhuluX","checkable":"false","checked":"false","clickable":"false","enabled":"true","focusable":"false","focused":"false","scrollable":"false","long-clickable":"false","password":"false","selected":"false","bounds":"[357,1492][407,1543]","node":{"index":"0","text":"FA","class":"android.widget.TextView","package":"com.ZhuluX","checkable":"false","checked":"false","clickable":"false","enabled":"true","focusable":"false","focused":"false","scrollable":"false","long-clickable":"false","password":"false","selected":"false","bounds":"[365,1497][399,1538]"}},{"index":"4","class":"android.widget.ImageView","package":"com.ZhuluX","checkable":"false","checked":"false","clickable":"false","enabled":"true","focusable":"false","focused":"false","scrollable":"false","long-clickable":"false","password":"false","selected":"false","bounds":"[164,1574][184,1603]"},{"index":"5","text":"成功创业经验 · 海归创业 · 具备技术壁垒","class":"android.widget.TextView","package":"com.ZhuluX","checkable":"false","checked":"false","clickable":"false","enabled":"true","focusable":"false","focused":"false","scrollable":"false","long-clickable":"false","password":"false","selected":"false","bounds":"[196,1568][728,1609]"},{"index":"7","text":"11111大发大水发打算发的撒11111大发大水发打算发的撒11111大发大水发打算发的撒11111大发大水发打算发的撒11111大发大水发打算发的撒11111大发大水发打算发的撒11111大发大水发打算发的撒11111大发大水发打算发的撒11111大发大水发打算发的撒11111大发大水发打算发的撒11111大发大水发打算发的撒11111大发大水发打算发的撒","class":"android.widget.TextView","package":"com.ZhuluX","checkable":"false","checked":"false","clickable":"false","enabled":"true","focusable":"false","focused":"false","scrollable":"false","long-clickable":"false","password":"false","selected":"false","bounds":"[39,1629][991,1751]"}]},{"index":"1","class":"android.widget.ImageView","package":"com.ZhuluX","checkable":"false","checked":"false","clickable":"false","enabled":"true","focusable":"false","focused":"false","scrollable":"false","long-clickable":"false","password":"false","selected":"false","bounds":"[948,1450][1028,1527]"}]}}]}}}}}]}]},{"index":"1","class":"android.view.ViewGroup","package":"com.ZhuluX","checkable":"false","checked":"false","clickable":"false","enabled":"true","focusable":"false","focused":"false","scrollable":"false","long-clickable":"false","password":"false","selected":"false","bounds":"[0,63][1080,1794]","node":[{"index":"2","class":"android.view.ViewGroup","package":"com.ZhuluX","checkable":"false","checked":"false","clickable":"false","enabled":"true","focusable":"false","focused":"false","scrollable":"false","long-clickable":"false","password":"false","selected":"false","bounds":"[0,63][1080,168]","node":[{"index":"0","class":"android.view.ViewGroup","package":"com.ZhuluX","checkable":"false","checked":"false","clickable":"false","enabled":"true","focusable":"true","focused":"false","scrollable":"false","long-clickable":"false","password":"false","selected":"false","bounds":"[39,88][92,143]","node":{"index":"0","text":"","class":"android.widget.TextView","package":"com.ZhuluX","checkable":"false","checked":"false","clickable":"false","enabled":"true","focusable":"false","focused":"false","scrollable":"false","long-clickable":"false","password":"false","selected":"false","bounds":"[39,88][92,143]"}},{"index":"1","text":"全部机构","class":"android.widget.TextView","package":"com.ZhuluX","checkable":"false","checked":"false","clickable":"false","enabled":"true","focusable":"false","focused":"false","scrollable":"false","long-clickable":"false","password":"false","selected":"false","bounds":"[450,85][630,146]"}]},{"index":"3","class":"android.widget.ScrollView","package":"com.ZhuluX","checkable":"false","checked":"false","clickable":"false","enabled":"true","focusable":"true","focused":"false","scrollable":"false","long-clickable":"false","password":"false","selected":"false","bounds":"[0,168][1080,1794]","node":{"index":"0","class":"android.view.ViewGroup","package":"com.ZhuluX","checkable":"false","checked":"false","clickable":"false","enabled":"true","focusable":"false","focused":"false","scrollable":"false","long-clickable":"false","password":"false","selected":"false","bounds":"[39,168][1041,1625]","node":[{"index":"0","class":"android.view.ViewGroup","package":"com.ZhuluX","checkable":"false","checked":"false","clickable":"false","enabled":"true","focusable":"true","focused":"false","scrollable":"false","long-clickable":"false","password":"false","selected":"false","bounds":"[39,168][1041,522]","node":{"index":"0","class":"android.view.ViewGroup","package":"com.ZhuluX","checkable":"false","checked":"false","clickable":"false","enabled":"true","focusable":"false","focused":"false","scrollable":"false","long-clickable":"false","password":"false","selected":"false","bounds":"[39,207][1041,522]","node":[{"index":"0","class":"android.widget.ImageView","package":"com.ZhuluX","checkable":"false","checked":"false","clickable":"false","enabled":"true","focusable":"false","focused":"false","scrollable":"false","long-clickable":"false","password":"false","selected":"false","bounds":"[39,207][1041,522]"},{"index":"1","class":"android.view.View","package":"com.ZhuluX","checkable":"false","checked":"false","clickable":"false","enabled":"true","focusable":"false","focused":"false","scrollable":"false","long-clickable":"false","password":"false","selected":"false","bounds":"[39,207][1041,522]"},{"index":"2","class":"android.widget.ImageView","package":"com.ZhuluX","checkable":"false","checked":"false","clickable":"false","enabled":"true","focusable":"false","focused":"false","scrollable":"false","long-clickable":"false","password":"false","selected":"false","bounds":"[65,207][130,291]"},{"index":"3","text":"2","class":"android.widget.TextView","package":"com.ZhuluX","checkable":"false","checked":"false","clickable":"false","enabled":"true","focusable":"false","focused":"false","scrollable":"false","long-clickable":"false","password":"false","selected":"false","bounds":"[86,207][110,249]"},{"index":"4","text":"NEW","class":"android.widget.TextView","package":"com.ZhuluX","checkable":"false","checked":"false","clickable":"false","enabled":"true","focusable":"false","focused":"false","scrollable":"false","long-clickable":"false","password":"false","selected":"false","bounds":"[75,249][121,270]"},{"index":"5","text":"逐鹿科技组","class":"android.widget.TextView","package":"com.ZhuluX","checkable":"false","checked":"false","clickable":"false","enabled":"true","focusable":"false","focused":"false","scrollable":"false","long-clickable":"false","password":"false","selected":"false","bounds":"[407,256][672,327]"},{"index":"6","class":"android.view.ViewGroup","package":"com.ZhuluX","checkable":"false","checked":"false","clickable":"false","enabled":"true","focusable":"true","focused":"false","scrollable":"false","long-clickable":"false","password":"false","selected":"false","bounds":"[836,233][1014,296]","node":[{"index":"0","text":"","class":"android.widget.TextView","package":"com.ZhuluX","checkable":"false","checked":"false","clickable":"false","enabled":"true","focusable":"false","focused":"false","scrollable":"false","long-clickable":"false","password":"false","selected":"false","bounds":"[850,233][882,296]"},{"index":"1","text":"已订阅","class":"android.widget.TextView","package":"com.ZhuluX","checkable":"false","checked":"false","clickable":"false","enabled":"true","focusable":"false","focused":"false","scrollable":"false","long-clickable":"false","password":"false","selected":"false","bounds":"[890,239][1001,290]"}]},{"index":"7","text":"房产服务，教育，文化娱乐，旅游，本地生活，汽车交通，物流，硬件","class":"android.widget.TextView","package":"com.ZhuluX","checkable":"false","checked":"false","clickable":"false","enabled":"true","focusable":"false","focused":"false","scrollable":"false","long-clickable":"false","password":"false","selected":"false","bounds":"[44,353][1036,396]"},{"index":"8","text":"4 个项目","class":"android.widget.TextView","package":"com.ZhuluX","checkable":"false","checked":"false","clickable":"false","enabled":"true","focusable":"false","focused":"false","scrollable":"false","long-clickable":"false","password":"false","selected":"false","bounds":"[469,422][610,473]"}]}},{"index":"1","class":"android.view.ViewGroup","package":"com.ZhuluX","checkable":"false","checked":"false","clickable":"false","enabled":"true","focusable":"true","focused":"false","scrollable":"false","long-clickable":"false","password":"false","selected":"false","bounds":"[39,522][1041,877]","node":{"index":"0","class":"android.view.ViewGroup","package":"com.ZhuluX","checkable":"false","checked":"false","clickable":"false","enabled":"true","focusable":"false","focused":"false","scrollable":"false","long-clickable":"false","password":"false","selected":"false","bounds":"[39,561][1041,876]","node":[{"index":"0","class":"android.widget.ImageView","package":"com.ZhuluX","checkable":"false","checked":"false","clickable":"false","enabled":"true","focusable":"false","focused":"false","scrollable":"false","long-clickable":"false","password":"false","selected":"false","bounds":"[39,561][1041,876]"},{"index":"1","class":"android.view.View","package":"com.ZhuluX","checkable":"false","checked":"false","clickable":"false","enabled":"true","focusable":"false","focused":"false","scrollable":"false","long-clickable":"false","password":"false","selected":"false","bounds":"[39,561][1041,876]"},{"index":"2","text":"华兴逐鹿文娱组","class":"android.widget.TextView","package":"com.ZhuluX","checkable":"false","checked":"false","clickable":"false","enabled":"true","focusable":"false","focused":"false","scrollable":"false","long-clickable":"false","password":"false","selected":"false","bounds":"[354,610][725,681]"},{"index":"3","class":"android.view.ViewGroup","package":"com.ZhuluX","checkable":"false","checked":"false","clickable":"false","enabled":"true","focusable":"true","focused":"false","scrollable":"false","long-clickable":"false","password":"false","selected":"false","bounds":"[836,587][1014,650]","node":[{"index":"0","text":"","class":"android.widget.TextView","package":"com.ZhuluX","checkable":"false","checked":"false","clickable":"false","enabled":"true","focusable":"false","focused":"false","scrollable":"false","long-clickable":"false","password":"false","selected":"false","bounds":"[850,587][882,650]"},{"index":"1","text":"已订阅","class":"android.widget.TextView","package":"com.ZhuluX","checkable":"false","checked":"false","clickable":"false","enabled":"true","focusable":"false","focused":"false","scrollable":"false","long-clickable":"false","password":"false","selected":"false","bounds":"[890,593][1001,644]"}]},{"index":"4","text":"工具软件，文化娱乐，旅游，本地生活","class":"android.widget.TextView","package":"com.ZhuluX","checkable":"false","checked":"false","clickable":"false","enabled":"true","focusable":"false","focused":"false","scrollable":"false","long-clickable":"false","password":"false","selected":"false","bounds":"[268,707][812,750]"},{"index":"5","text":"0 个项目","class":"android.widget.TextView","package":"com.ZhuluX","checkable":"false","checked":"false","clickable":"false","enabled":"true","focusable":"false","focused":"false","scrollable":"false","long-clickable":"false","password":"false","selected":"false","bounds":"[469,776][610,827]"}]}},{"index":"2","class":"android.view.ViewGroup","package":"com.ZhuluX","checkable":"false","checked":"false","clickable":"false","enabled":"true","focusable":"true","focused":"false","scrollable":"false","long-clickable":"false","password":"false","selected":"false","bounds":"[39,877][1041,1231]","node":{"index":"0","class":"android.view.ViewGroup","package":"com.ZhuluX","checkable":"false","checked":"false","clickable":"false","enabled":"true","focusable":"false","focused":"false","scrollable":"false","long-clickable":"false","password":"false","selected":"false","bounds":"[39,916][1041,1231]","node":[{"index":"0","class":"android.widget.ImageView","package":"com.ZhuluX","checkable":"false","checked":"false","clickable":"false","enabled":"true","focusable":"false","focused":"false","scrollable":"false","long-clickable":"false","password":"false","selected":"false","bounds":"[39,916][1041,1231]"},{"index":"1","class":"android.view.View","package":"com.ZhuluX","checkable":"false","checked":"false","clickable":"false","enabled":"true","focusable":"false","focused":"false","scrollable":"false","long-clickable":"false","password":"false","selected":"false","bounds":"[39,916][1041,1231]"},{"index":"2","text":"中后台","class":"android.widget.TextView","package":"com.ZhuluX","checkable":"false","checked":"false","clickable":"false","enabled":"true","focusable":"false","focused":"false","scrollable":"false","long-clickable":"false","password":"false","selected":"false","bounds":"[460,965][619,1036]"},{"index":"3","class":"android.view.ViewGroup","package":"com.ZhuluX","checkable":"false","checked":"false","clickable":"false","enabled":"true","focusable":"true","focused":"false","scrollable":"false","long-clickable":"false","password":"false","selected":"false","bounds":"[836,942][1014,1005]","node":{"index":"0","text":"+ 订阅","class":"android.widget.TextView","package":"com.ZhuluX","checkable":"false","checked":"false","clickable":"false","enabled":"true","focusable":"false","focused":"false","scrollable":"false","long-clickable":"false","password":"false","selected":"false","bounds":"[873,948][977,999]"}},{"index":"4","text":"金融","class":"android.widget.TextView","package":"com.ZhuluX","checkable":"false","checked":"false","clickable":"false","enabled":"true","focusable":"false","focused":"false","scrollable":"false","long-clickable":"false","password":"false","selected":"false","bounds":"[508,1062][572,1105]"},{"index":"5","text":"0 个项目","class":"android.widget.TextView","package":"com.ZhuluX","checkable":"false","checked":"false","clickable":"false","enabled":"true","focusable":"false","focused":"false","scrollable":"false","long-clickable":"false","password":"false","selected":"false","bounds":"[469,1131][610,1182]"}]}},{"index":"3","class":"android.view.ViewGroup","package":"com.ZhuluX","checkable":"false","checked":"false","clickable":"false","enabled":"true","focusable":"true","focused":"false","scrollable":"false","long-clickable":"false","password":"false","selected":"false","bounds":"[39,1231][1041,1625]","node":{"index":"0","class":"android.view.ViewGroup","package":"com.ZhuluX","checkable":"false","checked":"false","clickable":"false","enabled":"true","focusable":"false","focused":"false","scrollable":"false","long-clickable":"false","password":"false","selected":"false","bounds":"[39,1270][1041,1585]","node":[{"index":"0","class":"android.widget.ImageView","package":"com.ZhuluX","checkable":"false","checked":"false","clickable":"false","enabled":"true","focusable":"false","focused":"false","scrollable":"false","long-clickable":"false","password":"false","selected":"false","bounds":"[39,1270][1041,1585]"},{"index":"1","class":"android.view.View","package":"com.ZhuluX","checkable":"false","checked":"false","clickable":"false","enabled":"true","focusable":"false","focused":"false","scrollable":"false","long-clickable":"false","password":"false","selected":"false","bounds":"[39,1270][1041,1585]"},{"index":"2","text":"车房金融","class":"android.widget.TextView","package":"com.ZhuluX","checkable":"false","checked":"false","clickable":"false","enabled":"true","focusable":"false","focused":"false","scrollable":"false","long-clickable":"false","password":"false","selected":"false","bounds":"[434,1319][646,1390]"},{"index":"3","class":"android.view.ViewGroup","package":"com.ZhuluX","checkable":"false","checked":"false","clickable":"false","enabled":"true","focusable":"true","focused":"false","scrollable":"false","long-clickable":"false","password":"false","selected":"false","bounds":"[836,1296][1014,1359]","node":{"index":"0","text":"+ 订阅","class":"android.widget.TextView","package":"com.ZhuluX","checkable":"false","checked":"false","clickable":"false","enabled":"true","focusable":"false","focused":"false","scrollable":"false","long-clickable":"false","password":"false","selected":"false","bounds":"[873,1302][977,1353]"}},{"index":"4","text":"工具软件","class":"android.widget.TextView","package":"com.ZhuluX","checkable":"false","checked":"false","clickable":"false","enabled":"true","focusable":"false","focused":"false","scrollable":"false","long-clickable":"false","password":"false","selected":"false","bounds":"[476,1416][604,1459]"},{"index":"5","text":"0 个项目","class":"android.widget.TextView","package":"com.ZhuluX","checkable":"false","checked":"false","clickable":"false","enabled":"true","focusable":"false","focused":"false","scrollable":"false","long-clickable":"false","password":"false","selected":"false","bounds":"[469,1485][610,1536]"}]}}]}}]}]}}}}}}}}}}]}